src/demux.v
module demux (
    input  wire        din,      // 1-bit input data
    input  wire [5:0]  sel,      // 6-bit select signal (0 to 63)
    input  wire        enable,   // Active-high enable (optional, recommended)
    output reg  [63:0] dout      // 64-bit output vector
);

    always @(*) begin
        // Default state: all outputs set to 0
        dout = 64'b0;
        
        if (enable) begin
            // Bitwise shift left: places 'din' at index 'sel'
            dout[sel] = din;
        end
    end

endmodule

src/demuxtb.v


module demuxtb;

    // Testbench signals
    reg        din;
    reg  [5:0] sel;
    reg        enable;
    wire [63:0] dout;

    integer i;

    // Instantiate Design Under Test
    demux uut (
        .din(din),
        .sel(sel),
        .enable(enable),
        .dout(dout)
    );

    initial begin
        // --- VCD Dump Commands ---
        $dumpfile("demux.vcd"); // Name of the output VCD file
        $dumpvars(0, demuxtb);   // Dump all signals in the testbench hierarchy

        // Monitor outputs in terminal console
        $monitor("Time = %0t | enable = %b | din = %b | sel = %0d | dout = %h", 
                 $time, enable, din, sel, dout);

        // Signal initialization
        din    = 1'b0;
        sel    = 6'b0;
        enable = 1'b0;
        #10;

        // Test disabled state
        din    = 1'b1;
        sel    = 6'd15;
        enable = 1'b0;
        #10;

        // Sweep all 64 select lines
        enable = 1'b1;
        din    = 1'b1;

        for (i = 0; i < 64; i = i + 1) begin
            sel = i[5:0];
            #10;
        end

        // End simulation and close dump file
        $display("\n--- Dump File Generated Successfully ---");
        $finish;
    end

endmodule

src/demux.vcd
$date
	Fri Jul 24 06:58:12 2026
$end
$version
	Icarus Verilog
$end
$timescale
	1s
$end
$scope module demuxtb $end
$var wire 64 ! dout [63:0] $end
$var reg 1 " din $end
$var reg 1 # enable $end
$var reg 6 $ sel [5:0] $end
$var integer 32 % i [31:0] $end
$scope module uut $end
$var wire 1 " din $end
$var wire 1 # enable $end
$var wire 6 & sel [5:0] $end
$var reg 64 ' dout [63:0] $end
$upscope $end
$upscope $end
$enddefinitions $end
$comment Show the parameter values. $end
$dumpall
$end
#0
$dumpvars
b0 '
b0 &
bx %
b0 $
0#
0"
b0 !
$end
#10
b1111 $
b1111 &
1"
#20
b1 !
b1 '
b0 $
b0 &
b0 %
1#
#30
b10 !
b10 '
b1 $
b1 &
b1 %
#40
b100 !
b100 '
b10 $
b10 &
b10 %
#50
b1000 !
b1000 '
b11 $
b11 &
b11 %
#60
b10000 !
b10000 '
b100 $
b100 &
b100 %
#70
b100000 !
b100000 '
b101 $
b101 &
b101 %
#80
b1000000 !
b1000000 '
b110 $
b110 &
b110 %
#90
b10000000 !
b10000000 '
b111 $
b111 &
b111 %
#100
b100000000 !
b100000000 '
b1000 $
b1000 &
b1000 %
#110
b1000000000 !
b1000000000 '
b1001 $
b1001 &
b1001 %
#120
b10000000000 !
b10000000000 '
b1010 $
b1010 &
b1010 %
#130
b100000000000 !
b100000000000 '
b1011 $
b1011 &
b1011 %
#140
b1000000000000 !
b1000000000000 '
b1100 $
b1100 &
b1100 %
#150
b10000000000000 !
b10000000000000 '
b1101 $
b1101 &
b1101 %
#160
b100000000000000 !
b100000000000000 '
b1110 $
b1110 &
b1110 %
#170
b1000000000000000 !
b1000000000000000 '
b1111 $
b1111 &
b1111 %
#180
b10000000000000000 !
b10000000000000000 '
b10000 $
b10000 &
b10000 %
#190
b100000000000000000 !
b100000000000000000 '
b10001 $
b10001 &
b10001 %
#200
b1000000000000000000 !
b1000000000000000000 '
b10010 $
b10010 &
b10010 %
#210
b10000000000000000000 !
b10000000000000000000 '
b10011 $
b10011 &
b10011 %
#220
b100000000000000000000 !
b100000000000000000000 '
b10100 $
b10100 &
b10100 %
#230
b1000000000000000000000 !
b1000000000000000000000 '
b10101 $
b10101 &
b10101 %
#240
b10000000000000000000000 !
b10000000000000000000000 '
b10110 $
b10110 &
b10110 %
#250
b100000000000000000000000 !
b100000000000000000000000 '
b10111 $
b10111 &
b10111 %
#260
b1000000000000000000000000 !
b1000000000000000000000000 '
b11000 $
b11000 &
b11000 %
#270
b10000000000000000000000000 !
b10000000000000000000000000 '
b11001 $
b11001 &
b11001 %
#280
b100000000000000000000000000 !
b100000000000000000000000000 '
b11010 $
b11010 &
b11010 %
#290
b1000000000000000000000000000 !
b1000000000000000000000000000 '
b11011 $
b11011 &
b11011 %
#300
b10000000000000000000000000000 !
b10000000000000000000000000000 '
b11100 $
b11100 &
b11100 %
#310
b100000000000000000000000000000 !
b100000000000000000000000000000 '
b11101 $
b11101 &
b11101 %
#320
b1000000000000000000000000000000 !
b1000000000000000000000000000000 '
b11110 $
b11110 &
b11110 %
#330
b10000000000000000000000000000000 !
b10000000000000000000000000000000 '
b11111 $
b11111 &
b11111 %
#340
b100000000000000000000000000000000 !
b100000000000000000000000000000000 '
b100000 $
b100000 &
b100000 %
#350
b1000000000000000000000000000000000 !
b1000000000000000000000000000000000 '
b100001 $
b100001 &
b100001 %
#360
b10000000000000000000000000000000000 !
b10000000000000000000000000000000000 '
b100010 $
b100010 &
b100010 %
#370
b100000000000000000000000000000000000 !
b100000000000000000000000000000000000 '
b100011 $
b100011 &
b100011 %
#380
b1000000000000000000000000000000000000 !
b1000000000000000000000000000000000000 '
b100100 $
b100100 &
b100100 %
#390
b10000000000000000000000000000000000000 !
b10000000000000000000000000000000000000 '
b100101 $
b100101 &
b100101 %
#400
b100000000000000000000000000000000000000 !
b100000000000000000000000000000000000000 '
b100110 $
b100110 &
b100110 %
#410
b1000000000000000000000000000000000000000 !
b1000000000000000000000000000000000000000 '
b100111 $
b100111 &
b100111 %
#420
b10000000000000000000000000000000000000000 !
b10000000000000000000000000000000000000000 '
b101000 $
b101000 &
b101000 %
#430
b100000000000000000000000000000000000000000 !
b100000000000000000000000000000000000000000 '
b101001 $
b101001 &
b101001 %
#440
b1000000000000000000000000000000000000000000 !
b1000000000000000000000000000000000000000000 '
b101010 $
b101010 &
b101010 %
#450
b10000000000000000000000000000000000000000000 !
b10000000000000000000000000000000000000000000 '
b101011 $
b101011 &
b101011 %
#460
b100000000000000000000000000000000000000000000 !
b100000000000000000000000000000000000000000000 '
b101100 $
b101100 &
b101100 %
#470
b1000000000000000000000000000000000000000000000 !
b1000000000000000000000000000000000000000000000 '
b101101 $
b101101 &
b101101 %
#480
b10000000000000000000000000000000000000000000000 !
b10000000000000000000000000000000000000000000000 '
b101110 $
b101110 &
b101110 %
#490
b100000000000000000000000000000000000000000000000 !
b100000000000000000000000000000000000000000000000 '
b101111 $
b101111 &
b101111 %
#500
b1000000000000000000000000000000000000000000000000 !
b1000000000000000000000000000000000000000000000000 '
b110000 $
b110000 &
b110000 %
#510
b10000000000000000000000000000000000000000000000000 !
b10000000000000000000000000000000000000000000000000 '
b110001 $
b110001 &
b110001 %
#520
b100000000000000000000000000000000000000000000000000 !
b100000000000000000000000000000000000000000000000000 '
b110010 $
b110010 &
b110010 %
#530
b1000000000000000000000000000000000000000000000000000 !
b1000000000000000000000000000000000000000000000000000 '
b110011 $
b110011 &
b110011 %
#540
b10000000000000000000000000000000000000000000000000000 !
b10000000000000000000000000000000000000000000000000000 '
b110100 $
b110100 &
b110100 %
#550
b100000000000000000000000000000000000000000000000000000 !
b100000000000000000000000000000000000000000000000000000 '
b110101 $
b110101 &
b110101 %
#560
b1000000000000000000000000000000000000000000000000000000 !
b1000000000000000000000000000000000000000000000000000000 '
b110110 $
b110110 &
b110110 %
#570
b10000000000000000000000000000000000000000000000000000000 !
b10000000000000000000000000000000000000000000000000000000 '
b110111 $
b110111 &
b110111 %
#580
b100000000000000000000000000000000000000000000000000000000 !
b100000000000000000000000000000000000000000000000000000000 '
b111000 $
b111000 &
b111000 %
#590
b1000000000000000000000000000000000000000000000000000000000 !
b1000000000000000000000000000000000000000000000000000000000 '
b111001 $
b111001 &
b111001 %
#600
b10000000000000000000000000000000000000000000000000000000000 !
b10000000000000000000000000000000000000000000000000000000000 '
b111010 $
b111010 &
b111010 %
#610
b100000000000000000000000000000000000000000000000000000000000 !
b100000000000000000000000000000000000000000000000000000000000 '
b111011 $
b111011 &
b111011 %
#620
b1000000000000000000000000000000000000000000000000000000000000 !
b1000000000000000000000000000000000000000000000000000000000000 '
b111100 $
b111100 &
b111100 %
#630
b10000000000000000000000000000000000000000000000000000000000000 !
b10000000000000000000000000000000000000000000000000000000000000 '
b111101 $
b111101 &
b111101 %
#640
b100000000000000000000000000000000000000000000000000000000000000 !
b100000000000000000000000000000000000000000000000000000000000000 '
b111110 $
b111110 &
b111110 %
#650
b1000000000000000000000000000000000000000000000000000000000000000 !
b1000000000000000000000000000000000000000000000000000000000000000 '
b111111 $
b111111 &
b111111 %
#660
b1000000 %
